hudlink/__init__.py
hudlink/api_calls.py
hudlink/cli.py
hudlink/config.py
hudlink/file_utils.py
hudlink/hudlink_data_loading.py
hudlink/hudlink_eligibility_calculation.py
hudlink/hudlink_family_feature_engineering.py
hudlink/hudlink_fill_counties_and_allocation.py
hudlink/hudlink_final_outputs.py
hudlink/hudlink_income_cleaning_and_household_splitting.py
hudlink/hudlink_prisoner_adjustment.py
hudlink/hudlink_processing.py
hudlink/hudlink_visuals.py
hudlink/main.py
hudlink/state_processor.py
hudlink/ui.py
hudlink-3.1.0.dist-info/licenses/LICENSE
hudlink-3.1.0.dist-info/METADATA
hudlink-3.1.0.dist-info/WHEEL
hudlink-3.1.0.dist-info/entry_points.txt
hudlink-3.1.0.dist-info/top_level.txt
hudlink-3.1.0.dist-info/RECORD
