Metadata-Version: 2.4
Name: hudlink
Version: 3.1.0
Summary: Automated ACS-HUD data linking for housing analysis: eligibility determination, protected-class analysis, and analysis-ready county summaries
Author-email: Shane Dabney <sdabney@fsu.edu>
License-Expression: MIT
Project-URL: Homepage, https://github.com/sdabney5/hudlink
Project-URL: Bug Tracker, https://github.com/sdabney5/hudlink/issues
Project-URL: Documentation, https://github.com/sdabney5/hudlink#readme
Keywords: housing-economics,housing-policy,affordable-housing,HUD,ACS,economic-analysis,policy-research,urban-planning
Classifier: Development Status :: 4 - Beta
Classifier: Intended Audience :: Science/Research
Classifier: Intended Audience :: Developers
Classifier: Intended Audience :: Financial and Insurance Industry
Classifier: Topic :: Scientific/Engineering :: Information Analysis
Classifier: Topic :: Scientific/Engineering :: GIS
Classifier: Programming Language :: Python :: 3
Classifier: Programming Language :: Python :: 3.9
Classifier: Programming Language :: Python :: 3.10
Classifier: Programming Language :: Python :: 3.11
Classifier: Operating System :: OS Independent
Requires-Python: >=3.9
License-File: LICENSE
Requires-Dist: pandas>=1.3.0
Requires-Dist: numpy>=1.20.0
Requires-Dist: ipumspy>=0.1.0
Requires-Dist: plotly>=5.0.0
Provides-Extra: test
Requires-Dist: pytest>=6.0; extra == "test"
Requires-Dist: pytest-cov>=3.0; extra == "test"
Dynamic: license-file
